haystack_brightdata/__init__.py
haystack_brightdata/_utilities.py
haystack_brightdata/brightdata_scraper.py
haystack_brightdata/brightdata_serp.py
haystack_brightdata/brightdata_unlocker.py
haystack_brightdata/datasets.py
haystack_brightdata/py.typed
haystack_brightdata-0.1.0.dist-info/METADATA
haystack_brightdata-0.1.0.dist-info/WHEEL
haystack_brightdata-0.1.0.dist-info/licenses/LICENSE
haystack_brightdata-0.1.0.dist-info/RECORD
