Metadata-Version: 2.4
Name: haystack-brightdata
Version: 0.1.0
Summary: Bright Data integration for Haystack - web scraping, SERP API, and data extraction from 45+ websites
Project-URL: Homepage, https://github.com/brightdata/haystack-brightdata
Project-URL: Documentation, https://github.com/brightdata/haystack-brightdata#readme
Project-URL: Repository, https://github.com/brightdata/haystack-brightdata
Project-URL: Issues, https://github.com/brightdata/haystack-brightdata/issues
Author-email: Bright Data <support@brightdata.com>
License: Apache-2.0
License-File: LICENSE
Keywords: amazon,brightdata,data-extraction,haystack,instagram,linkedin,serp,web-scraping,web-unlocker
Classifier: Development Status :: 4 - Beta
Classifier: Intended Audience :: Developers
Classifier: License :: OSI Approved :: Apache Software License
Classifier: Programming Language :: Python :: 3
Classifier: Programming Language :: Python :: 3.8
Classifier: Programming Language :: Python :: 3.9
Classifier: Programming Language :: Python :: 3.10
Classifier: Programming Language :: Python :: 3.11
Classifier: Programming Language :: Python :: 3.12
Classifier: Topic :: Internet :: WWW/HTTP :: Indexing/Search
Classifier: Topic :: Software Development :: Libraries :: Python Modules
Classifier: Topic :: Text Processing :: General
Requires-Python: >=3.8
Requires-Dist: aiohttp>=3.8.0
Requires-Dist: haystack-ai>=2.0.0
Requires-Dist: pydantic>=2.0.0
Requires-Dist: requests>=2.28.0
Provides-Extra: dev
Requires-Dist: black>=23.0.0; extra == 'dev'
Requires-Dist: mypy>=1.0.0; extra == 'dev'
Requires-Dist: pytest-asyncio>=0.21.0; extra == 'dev'
Requires-Dist: pytest-cov>=4.0.0; extra == 'dev'
Requires-Dist: pytest>=7.0.0; extra == 'dev'
Requires-Dist: ruff>=0.1.0; extra == 'dev'
Requires-Dist: types-requests>=2.28.0; extra == 'dev'
